pycolorlogs/__init__.py
pycolorlogs/colors.py
pycolorlogs/py.typed
pycolorlogs-1.1.3.dist-info/LICENSE
pycolorlogs-1.1.3.dist-info/METADATA
pycolorlogs-1.1.3.dist-info/WHEEL
pycolorlogs-1.1.3.dist-info/top_level.txt
pycolorlogs-1.1.3.dist-info/RECORD
