Metadata-Version: 2.1
Name: pycolorlogs
Version: 1.1.3
Summary: Extends default python logging package to include 256-bit terminal colors
Author-email: Pedro Menegasso <pvgmenegasso@gmail.com>
License: GNU GENERAL PUBLIC LICENSE
Project-URL: Homepage, https://github.com/pvgmenegasso/pycolorlogs
Keywords: logging,colors,output,devops,cli,unix
Classifier: License :: OSI Approved :: GNU General Public License v3 or later (GPLv3+)
Classifier: Programming Language :: Python
Classifier: Programming Language :: Python :: 3
Classifier: Topic :: System :: Logging
Classifier: Topic :: Software Development :: Libraries :: Python Modules
Classifier: Operating System :: OS Independent
Requires-Python: >=3.7.14
License-File: LICENSE
Requires-Dist: dataclasses
Requires-Dist: typing-extensions
